MANIFEST.in
README.rst
setup.py
scalation_kernel/__init__.py
scalation_kernel/__main__.py
scalation_kernel/install.py
scalation_kernel/kernel.py
scalation_kernel/templates.py
scalation_kernel.egg-info/PKG-INFO
scalation_kernel.egg-info/SOURCES.txt
scalation_kernel.egg-info/dependency_links.txt
scalation_kernel.egg-info/requires.txt
scalation_kernel.egg-info/top_level.txt