Metadata-Version: 1.1
Name: scalation-kernel
Version: 1.1.20
Summary: ScalaTion kernel for Jupyter
Home-page: https://github.com/scalation/scalation_kernel
Author: Michael E. Cotterell
Author-email: mepcott@uga.edu
License: UNKNOWN
Keywords: jupyter kernel scala scalation
Platform: UNKNOWN
Classifier: Development Status :: 3 - Alpha
Classifier: Intended Audience :: Developers
Classifier: Intended Audience :: Education
Classifier: Intended Audience :: Science/Research
Classifier: Topic :: Education
Classifier: Framework :: Jupyter
Classifier: License :: OSI Approved :: MIT License
Classifier: Programming Language :: Python :: 3
Classifier: Natural Language :: English
